callspect_cli.py
callspect/__init__.py
callspect/app.py
callspect/config.py
callspect/utils.py
callspect/static/call-tree.html
callspect/static/callspect-viewer.html
callspect/static/prism-line-highlight.css.html
callspect/static/prism-line-numbers.css.html
callspect/static/prism-theme-default.html
callspect/static/sequence-diagram.html
callspect/static/src-code.html
callspect/static/bower_components/bower-webfontloader/webfont.js
callspect/static/bower_components/eve-raphael/e.html
callspect/static/bower_components/eve-raphael/eve.js
callspect/static/bower_components/iron-ajax/index.html
callspect/static/bower_components/iron-ajax/iron-ajax.html
callspect/static/bower_components/iron-ajax/iron-request.html
callspect/static/bower_components/iron-ajax/demo/index.html
callspect/static/bower_components/iron-ajax/test/index.html
callspect/static/bower_components/iron-ajax/test/iron-ajax.html
callspect/static/bower_components/iron-ajax/test/iron-request.html
callspect/static/bower_components/js-sequence-diagrams/dist/sequence-diagram-min.js
callspect/static/bower_components/js-sequence-diagrams/dist/sequence-diagram-raphael-min.js
callspect/static/bower_components/js-sequence-diagrams/dist/sequence-diagram-raphael.js
callspect/static/bower_components/js-sequence-diagrams/dist/sequence-diagram-snap-min.js
callspect/static/bower_components/js-sequence-diagrams/dist/sequence-diagram-snap.js
callspect/static/bower_components/js-sequence-diagrams/dist/sequence-diagram.js
callspect/static/bower_components/js-sequence-diagrams/fonts/daniel/daniel-demo.html
callspect/static/bower_components/js-sequence-diagrams/fonts/daniel/daniel_400.font.js
callspect/static/bower_components/js-sequence-diagrams/fonts/daniel/daniel_700.font.js
callspect/static/bower_components/js-sequence-diagrams/fonts/daniel/daniel_black_900.font.js
callspect/static/bower_components/js-sequence-diagrams/fonts/daniel/danielbd-demo.html
callspect-0.1.3.dist-info/DESCRIPTION.rst
callspect-0.1.3.dist-info/METADATA
callspect-0.1.3.dist-info/RECORD
callspect-0.1.3.dist-info/WHEEL
callspect-0.1.3.dist-info/entry_points.txt
callspect-0.1.3.dist-info/metadata.json
callspect-0.1.3.dist-info/top_level.txt
