Metadata-Version: 2.0
Name: callspect
Version: 0.1.3
Summary: Inspect program execution from data generated by `callspectpy`
Home-page: https://github.com/xliiv/callspect
Author: xliiv
Author-email: tymoteusz.jankowski@gmail.com
License: MIT
Platform: UNKNOWN
Classifier: Programming Language :: Python :: 3
Requires-Python: >=3.5
Requires-Dist: Flask (==0.12.2)
